Metadata-Version: 1.1
Name: ofxstatement-be-cbc
Version: 0.1.1
Summary: ofxstatement plugin for parsing Belgian CBC bank's CSV statements to OFX
Home-page: https://github.com/tdhollander/ofxstatement-be-cbc
Author: Thomas D'Hollander, based on the version of Pieter Lenaerts
Author-email: thomas@dhollander.info
License: GPLv3
Keywords: ofx,banking,statement,cbc,csv
Platform: UNKNOWN
Classifier: Development Status :: 5 - Production/Stable
Classifier: Programming Language :: Python :: 3
Classifier: Natural Language :: English
Classifier: Topic :: Office/Business :: Financial :: Accounting
Classifier: Topic :: Utilities
Classifier: Environment :: Console
Classifier: Operating System :: OS Independent
Classifier: License :: OSI Approved :: GNU General Public License v3 (GPLv3)
